{
	"header": [
	{
		"text": "FABULOUS BEAUTY PERTH Pty Ltd",
		"size": 10,
		"bold": true,
		"align": 1,
		"line": true,
		"type": 0
	},
	{
		"text": "Northbridge",
		"size": 10,
		"bold": true,
		"align": 1,
		"line": true,
		"type": 0
	},
	{
		"text": "Tax Invoice",
		"size": 9,
		"bold": true,
		"align": 1,
		"line": true,
		"type": 0
	},
	{
		"text": "ABN：83 607 054 697",
		"size": 9,
		"bold": false,
		"align": 0,
		"line": true,
		"type": 0
	},
	
	{
		"text": "Cashier：{$cashier}",
		"size": 9,
		"bold": false,
		"align": 0,
		"line": true,
		"type": 0
	},
	{
		"text": "Purchase time：{$dateTime}",
		"size": 9,
		"bold": false,
		"align": 0,
		"line": true,
		"type": 0
	},
	{
		"text": "OrderNo：{$orderNo}",
		"size": 9,
		"bold": false,
		"align": 0,
		"line": true,
		"type": 0
	},
	{
		"text": "---------------------------------------",
		"size": 9,
		"bold": false,
		"align": 0,
		"line": true,
		"type": 0
	}],
	
	"goods": [{
		"name": "Name",
		"width": 20,
		"size":9,
		"bold": false,
		"variable": "name"
	},
	{
		"name": "Price",
		"width": 8,
		"size":9,
		"bold": false,
		"variable": "price"
	},
	{
		"name": "Quantity",
		"width": 10,
		"size":9,
		"bold": false,
		"variable": "amount"
	},
	{
		"name": "SubTotal",
		"width": 9,
		"size":9,
		"bold": false,
		"variable": "subTotal"
	}],
	

	"msg": [{
		"text": "---------------------------------------",
		"size": 9,
		"bold": false,
		"align": 0,
		"line": true,
		"type": 0
	},
	{
		"text": "Origin Price:             ${$originPrice}",
		"size": 8,
		"bold": false,
		"align": 0,
		"line": true,
		"type": 0
	},
	{
		"text": "Total:                    ${$totalPrice}",
		"size": 8,
		"bold": false,
		"align": 0,
		"line": true,
		"type": 0
	},
	
	{
		"text": "GST:                      ${$gst}",
		"size": 8,
		"bold": false,
		"align": 0,
		"line": true,
		"type": 0
	},
	{
		"text": "Payment Type:             {$payWay}",
		"size": 8,
		"bold": false,
		"align": 0,
		"line": true,
		"type": 0
	},
	{
		"text": "Member：{$member}",
		"size": 8,
		"bold": false,
		"align": 0,
		"line": true,
		"type": 0
	},
	{
		"text": "---------------------------------------",
		"size": 9,
		"bold": false,
		"align": 0,
		"line": true,
		"type": 0
	},
	{
		"text": "Address: 411 William St, Northbridge, WA",
		"size": 8,
		"bold": false,
		"align": 0,
		"line": true,
		"type": 0
	},
	{
		"text": "Add us on Wechat : Fabulousbeauty",
		"size": 9,
		"bold": false,
		"align": 0,
		"line": true,
		"type": 0
	},
	{
		"text": "Return Policy:",
		"size": 9,
		"bold": false,
		"align": 0,
		"line": true,
		"type": 0
	},
	{
		"text": "If you change your mind about the products you",
		"size": 8,
		"bold": false,
		"align": 0,
		"line": true,
		"type": 0
	},
	{
		"text": "have purchased from us, we can refund the pur-",
		"size": 8,
		"bold": false,
		"align": 0,
		"line": true,
		"type": 0
	},
	{
		"text": "chase the purchase price or exchange those pro-",
		"size": 8,
		"bold": false,
		"align": 0,
		"line": true,
		"type": 0
	},
	{
		"text": "ducts subject to the following conditions",
		"size": 8,
		"bold": false,
		"align": 0,
		"line": true,
		"type": 0
	},
	{
		"text": "*Items(s) must be returned or exchanged within",
		"size": 8,
		"bold": false,
		"align": 0,
		"line": true,
		"type": 0
	},
	{
		"text": "7 days of purchase together with the receipt.",
		"size": 8,
		"bold": false,
		"align": 0,
		"line": true,
		"type": 0
	},
	{
		"text": "*Item(s) must be unused and kept in original",
		"size": 8,
		"bold": false,
		"align": 0,
		"line": true,
		"type": 0
	},
	{
		"text": "condition.",
		"size": 8,
		"bold": false,
		"align": 0,
		"line": true,
		"type": 0
	},
	{
		"text": "*No cash refund.",
		"size": 8,
		"bold": false,
		"align": 0,
		"line": true,
		"type": 0
	},
	{
		"text": "*Clothes purchased in store cannot be refunded.",
		"size": 8,
		"bold": false,
		"align": 0,
		"line": true,
		"type": 0
	},
	{
		"text": "You can exchange within 7 days of purchase, ",
		"size": 8,
		"bold": false,
		"align": 0,
		"line": true,
		"type": 0
	},
	{
		"text": "together with the receipt. Original label must",
		"size": 8,
		"bold": false,
		"align": 0,
		"line": true,
		"type": 0
	},
	{
		"text": "be attached.",
		"size": 8,
		"bold": false,
		"align": 0,
		"line": true,
		"type": 0
	},
	{
		"text": "Thank you. :)",
		"size": 8,
		"bold": false,
		"align": 0,
		"line": true,
		"type": 0
	},
	{
		"text": "-",
		"size": 9,
		"bold": false,
		"align": 0,
		"line": true,
		"type": 0
	},
	{
		"text": "-",
		"size": 9,
		"bold": false,
		"align": 0,
		"line": true,
		"type": 0
	}
	]
}