{
	"header": [
	{
		"text": "FABULOUS BEAUTY PERTH Pty Ltd",
		"size": 10,
		"bold": true,
		"align": 1,
		"line": true,
		"type": 0
	},
	{
		"text": "Northbridge",
		"size": 10,
		"bold": true,
		"align": 1,
		"line": true,
		"type": 0
	},
	{
		"text": "ShiftWork",
		"size": 9,
		"bold": true,
		"align": 1,
		"line": true,
		"type": 0
	},
	{
		"text": "ABN：83 607 054 697",
		"size": 9,
		"bold": false,
		"align": 0,
		"line": true,
		"type": 0
	},
	{
		"text": "Cashier：{$Cashier}   ",
		"size": 9,
		"bold": false,
		"align": 0,
		"line": true,
		"type": 0
	},
	{
		"text": "Start Time：{$startTime}   ",
		"size": 9,
		"bold": false,
		"align": 0,
		"line": true,
		"type": 0
	},
	{
		"text": "End Time：{$endTime}   ",
		"size": 9,
		"bold": false,
		"align": 0,
		"line": true,
		"type": 0
	},
	{
		"text": "Duration：{$workHours}   ",
		"size": 9,
		"bold": false,
		"align": 0,
		"line": true,
		"type": 0
	},
	{
		"text": "Total Order：{$indentAmount}   ",
		"size": 9,
		"bold": false,
		"align": 0,
		"line": false,
		"type": 0
	},
	{
		"text": "Goods Quantity：{$goodsAmount}   ",
		"size": 9,
		"bold": false,
		"align": 0,
		"line": true,
		"type": 0
	},
	{
		"text": "Total Money：{$totalPrice}   ",
		"size": 9,
		"bold": false,
		"align": 0,
		"line": true,
		"type": 0
	},
	{
		"text": "Received Money：{$paidPrice}   ",
		"size": 9,
		"bold": false,
		"align": 0,
		"line": true,
		"type": 0
	},
	{
		"text": "Cash：{$cashMoney}   ",
		"size": 9,
		"bold": false,
		"align": 0,
		"line": false,
		"type": 0
	},
	{
		"text": "Bankcard：{$bankcardMoney}   ",
		"size": 9,
		"bold": false,
		"align": 0,
		"line": true,
		"type": 0
	},

	{
		"text": "---------------------------------------",
		"size": 9,
		"bold": false,
		"align": 0,
		"line": true,
		"type": 0
	}],
	
	"goods": [{
		"name": "Name",
		"width": 20,
		"size":9,
		"bold": false,
		"variable": "name"
	},
	{
		"name": "Price",
		"width": 8,
		"size":9,
		"bold": false,
		"variable": "price"
	},
	{
		"name": "Quantity",
		"width": 10,
		"size":9,
		"bold": false,
		"variable": "amount"
	},
	{
		"name": "SubTotal",
		"width": 5,
		"size":9,
		"bold": false,
		"variable": "subTotal"
	}],
	
	"msg": [
	{
		"text": "---------------------------------------",
		"size": 9,
		"bold": false,
		"align": 0,
		"line": true,
		"type": 0
	},
	{
		"text": "-",
		"size": 9,
		"bold": false,
		"align": 0,
		"line": true,
		"type": 0
	},
	{
		"text": "-",
		"size": 9,
		"bold": false,
		"align": 0,
		"line": true,
		"type": 0
	}
	]
}